03_basics/fifo.v
module fifo #(
    parameter DATA_WIDTH=8,
    parameter DEPTH = 4 
    )(
        input clk, 
        input rst,
        input write_en,
        input read_en,
        input [DATA_WIDTH-1:0] write_data,
        output reg [DATA_WIDTH-1:0] read_data,

        output full,
        output empty
    );
    localparam ADDR_WIDTH = $clog2(DEPTH);
    reg [DATA_WIDTH-1:0] memory [DEPTH-1:0];
    reg [ADDR_WIDTH-1:0] write_ptr; 
    reg [ADDR_WIDTH-1:0] read_ptr;
    reg [ADDR_WIDTH:0] count; 

    always @(posedge clk) begin
        if(rst) begin
            write_ptr <= 0;
            read_ptr <= 0; 
            count <= 0;
        end
        else begin
            if(write_en && !full) begin
                memory[write_ptr] <= write_data;
                write_ptr <= write_ptr + 1;
            end
            if(read_en && !empty) begin
                read_data <= memory[read_ptr]; 
                read_ptr <= read_ptr + 1;
            end
            if((write_en && !full) && !(read_en && !empty))
            count <= count + 1;
            else if((read_en && !empty) && !(write_en && !full))
            count <= count - 1;
        end
    end

    assign full = (count == DEPTH); 
    assign empty = (count == 0);
endmodule

03_basics/fifo_tb.v
module fifo_tb;

reg clk;
reg rst;
reg write_en;
reg read_en;
reg [7:0] write_data;

wire [7:0] read_data;
wire full;
wire empty;

fifo dut(
    .clk(clk),
    .rst(rst),
    .write_en(write_en),
    .read_en(read_en),
    .write_data(write_data),
    .read_data(read_data),
    .full(full),
    .empty(empty)
);

always #5 clk = ~clk;

initial begin
    $dumpfile("fifo.vcd");
    $dumpvars(0, fifo_tb);

    clk = 0;
    rst = 1;
    write_en = 0;
    read_en = 0;
    write_data = 0;
    $monitor("t=%0t write=%b read=%b data_in=%h data_out=%h full=%b empty=%b",
         $time, write_en, read_en, write_data, read_data, full, empty);

    #8 rst=0;
    #2 write_en=1; write_data = 8'b10101010; 
    #10 write_en=1; write_data = 8'b10111110;
    #10 write_en=1; write_data = 8'b10101000;
    #10 write_en=1; write_data = 8'b10101000; read_en = 1;
    #10 write_en=0; read_en=1;
    #10 read_en=1;
    #10 read_en=1;
    
//5 15 25 35 45 55 65 clk
//15 write 25 write 35 write 45 wrtie 55 read 65 read 75 read 

    #10 $finish;

end

endmodule

03_basics/fifo.vcd
$date
	Mon Sep  7 11:50:03 2026
$end
$version
	Icarus Verilog
$end
$timescale
	1s
$end
$scope module fifo_tb $end
$var wire 8 ! read_data [7:0] $end
$var wire 1 " full $end
$var wire 1 # empty $end
$var reg 1 $ clk $end
$var reg 1 % read_en $end
$var reg 1 & rst $end
$var reg 8 ' write_data [7:0] $end
$var reg 1 ( write_en $end
$scope module dut $end
$var wire 1 $ clk $end
$var wire 1 % read_en $end
$var wire 1 & rst $end
$var wire 8 ) write_data [7:0] $end
$var wire 1 ( write_en $end
$var wire 1 " full $end
$var wire 1 # empty $end
$var parameter 32 * ADDR_WIDTH $end
$var parameter 32 + DATA_WIDTH $end
$var parameter 32 , DEPTH $end
$var reg 3 - count [2:0] $end
$var reg 8 . read_data [7:0] $end
$var reg 2 / read_ptr [1:0] $end
$var reg 2 0 write_ptr [1:0] $end
$upscope $end
$upscope $end
$enddefinitions $end
$comment Show the parameter values. $end
$dumpall
b100 ,
b1000 +
b10 *
$end
#0
$dumpvars
bx 0
bx /
bx .
bx -
b0 )
0(
b0 '
1&
0%
0$
x#
x"
bx !
$end
#5
0"
1#
b0 -
b0 /
b0 0
1$
#8
0&
#10
b10101010 '
b10101010 )
1(
0$
#15
0#
b1 -
b1 0
1$
#20
0$
b10111110 '
b10111110 )
#25
b10 -
b10 0
1$
#30
0$
b10101000 '
b10101000 )
#35
b11 -
b11 0
1$
#40
0$
1%
#45
b1 /
b10101010 !
b10101010 .
b0 0
1$
#50
0$
0(
#55
b10 -
b10 /
b10111110 !
b10111110 .
1$
#60
0$
#65
b1 -
b11 /
b10101000 !
b10101000 .
1$
#70
0$
#75
1#
b0 -
b0 /
1$
